quickNAT_pytorch-1.3.dist-info/DESCRIPTION.rst
quickNAT_pytorch-1.3.dist-info/METADATA
quickNAT_pytorch-1.3.dist-info/RECORD
quickNAT_pytorch-1.3.dist-info/WHEEL
quickNAT_pytorch-1.3.dist-info/metadata.json
quickNAT_pytorch-1.3.dist-info/top_level.txt
quickNat_pytorch/__init__.py
quickNat_pytorch/data_utils.py
quickNat_pytorch/quickNAT.py
quickNat_pytorch/solver.py
quickNat_pytorch/net_api/__init__.py
quickNat_pytorch/net_api/losses.py
quickNat_pytorch/net_api/sub_module.py
