Metadata-Version: 2.0
Name: quickNAT-pytorch
Version: 1.3
Summary: QuickNAT, Brain segmentation.
Home-page: https://github.com/abhi4ssj/quickNAT_pytorch
Author: Abhijit Guha Roy
Author-email: abhi4ssj@gmail.com
License: UNKNOWN
Platform: UNKNOWN
